CHANGES.txt
MANIFEST.in
README.rst
pytest.ini
setup.py
pyramid_peewee_conn/__init__.py
pyramid_peewee_conn.egg-info/PKG-INFO
pyramid_peewee_conn.egg-info/SOURCES.txt
pyramid_peewee_conn.egg-info/dependency_links.txt
pyramid_peewee_conn.egg-info/not-zip-safe
pyramid_peewee_conn.egg-info/requires.txt
pyramid_peewee_conn.egg-info/top_level.txt
pyramid_peewee_conn/tests/__init__.py
pyramid_peewee_conn/tests/config.ini