Metadata-Version: 1.1
Name: pyramid-peewee-conn
Version: 0.7.1
Summary: Provides integration between the Pyramid web application and the peewee ORM.
Home-page: https://github.com/inpool/pyramid_peewee_conn
Author: Inpool
Author-email: inpool@126.com
License: UNKNOWN
Keywords: web pyramid peewee
Platform: UNKNOWN
Classifier: Programming Language :: Python
Classifier: Framework :: Pyramid
Classifier: Topic :: Internet :: WWW/HTTP
Classifier: Topic :: Internet :: WWW/HTTP :: WSGI :: Application
Classifier: Topic :: Database
